kmac_automl/AutoML_AnomalyDetection.py
kmac_automl/AutoML_Classification.py
kmac_automl/AutoML_Clustering.py
kmac_automl/AutoML_Regression.py
kmac_automl/AutoML_TimeSeries.py
kmac_automl/__init__.py
kmac_automl-1.1.4.dist-info/LICENSE.md
kmac_automl-1.1.4.dist-info/METADATA
kmac_automl-1.1.4.dist-info/WHEEL
kmac_automl-1.1.4.dist-info/top_level.txt
kmac_automl-1.1.4.dist-info/RECORD
